{
    "menu": [{
        "id": "menu_motor",
        "text": "Motor",
        "icon": "icon-motor",
        "onClick": "",
        "dropdown": [{
            "id": "menu_motor_start",
            "text": "Start Inverter",
            "icon": "icon-key",
            "onClick": "new bootstrap.Modal(document.getElementById('startInverterMode'), {}).show()"
        }, {
            "id": "menu_motor_stop",
            "text": "Stop Inverter",
            "icon": "icon-alert",
            "onClick": "stopInverter()"
        }, {
            "id": "menu_motor_default",
            "text": "Reset to Default",
            "icon": "icon-reset",
            "onClick": "new bootstrap.Modal(document.getElementById('resetInverterDefault'), {}).show()"
        }, {
            "id": "-"
        }, {
            "id": "menu_motor_parameters",
            "text": "Parameters",
            "icon": "icon-settings",
            "onClick": "/index.php"
        }, {
            "id": "menu_motor_graph",
            "text": "Graph",
            "icon": "icon-graph-bar",
            "onClick": "/graph.php"
        }, {
            "id": "menu_motor_db",
            "text": "Motor Database",
            "icon": "icon-magic",
            "onClick": "https://openinverter.org/parameters"
        }, {
            "id": "-"
        }, {
            "id": "menu_motor_tuning",
            "text": "Auto Tuning",
            "icon": "icon-tune",
            "onClick": "/simple.php"
        }, {
            "id": "menu_motor_can",
            "text": "CAN Mapping",
            "icon": "icon-list",
            "onClick": "/can.php"
        }]
    }, {
        "id": "menu_inverter",
        "text": "Inverter",
        "icon": "icon-inverter",
        "onClick": "",
        "dropdown": [{
            "id": "menu_inverter_esp8266",
            "text": "Flash ESP8266",
            "icon": "icon-wifi",
            "onClick": "/esp8266.php"
        }, {
            "id": "menu_inverter_bootloader",
            "text": "Flash Bootloader",
            "icon": "icon-chip",
            "onClick": "/bootloader.php"
        }, {
            "id": "menu_inverter_firmware",
            "text": "Flash Firmware",
            "icon": "icon-ram",
            "onClick": "/firmware.php"
        }, {
            "id": "-"
        }, {
            "id": "menu_inverter_test",
            "text": "Board Test",
            "icon": "icon-test",
            "onClick": "/test.php"
        }]
    }]
}